betterproto/__init__.py
betterproto/_types.py
betterproto/_version.py
betterproto/casing.py
betterproto/compile/__init__.py
betterproto/compile/importing.py
betterproto/compile/naming.py
betterproto/enum.py
betterproto/grpcstub/__init__.py
betterproto/grpcstub/grpcio_client.py
betterproto/grpcstub/grpcio_server.py
betterproto/grpcstub/grpclib_client.py
betterproto/grpcstub/grpclib_server.py
betterproto/grpcstub/util/__init__.py
betterproto/grpcstub/util/async_channel.py
betterproto/lib/__init__.py
betterproto/lib/google/__init__.py
betterproto/lib/google/protobuf/__init__.py
betterproto/lib/google/protobuf/compiler/__init__.py
betterproto/lib/pydantic/__init__.py
betterproto/lib/pydantic/google/__init__.py
betterproto/lib/pydantic/google/protobuf/__init__.py
betterproto/lib/pydantic/google/protobuf/compiler/__init__.py
betterproto/lib/std/__init__.py
betterproto/lib/std/google/__init__.py
betterproto/lib/std/google/protobuf/__init__.py
betterproto/lib/std/google/protobuf/compiler/__init__.py
betterproto/plugin/__init__.py
betterproto/plugin/__main__.py
betterproto/plugin/compiler.py
betterproto/plugin/main.py
betterproto/plugin/models.py
betterproto/plugin/parser.py
betterproto/plugin/plugin.bat
betterproto/py.typed
betterproto/templates/template.py.j2
betterproto/utils.py
betterproto_beta9-2.0.1.dist-info/LICENSE.md
betterproto_beta9-2.0.1.dist-info/METADATA
betterproto_beta9-2.0.1.dist-info/WHEEL
betterproto_beta9-2.0.1.dist-info/entry_points.txt
betterproto_beta9-2.0.1.dist-info/RECORD
