Metadata-Version: 2.1
Name: betterproto-beta9
Version: 2.0.1
Summary: A better Protobuf / gRPC generator & library
Home-page: https://github.com/beam-cloud/python-betterproto
License: MIT
Keywords: protobuf,gRPC
Author: Daniel G. Taylor
Author-email: danielgtaylor@gmail.com
Requires-Python: >=3.8,<4.0
Classifier: License :: OSI Approved :: MIT License
Classifier: Programming Language :: Python :: 3
Classifier: Programming Language :: Python :: 3.8
Classifier: Programming Language :: Python :: 3.9
Classifier: Programming Language :: Python :: 3.10
Classifier: Programming Language :: Python :: 3.11
Classifier: Programming Language :: Python :: 3.12
Classifier: Programming Language :: Python :: 3.13
Provides-Extra: compiler
Provides-Extra: grpcio
Provides-Extra: rust-codec
Requires-Dist: betterproto-rust-codec (==0.1.1) ; extra == "rust-codec"
Requires-Dist: black (>=23.1.0) ; extra == "compiler"
Requires-Dist: grpcio (>=1.64.0,<2.0.0) ; extra == "grpcio"
Requires-Dist: grpclib (>=0.4.1,<0.5.0)
Requires-Dist: importlib-metadata (>=1.6.0) ; python_version < "3.8"
Requires-Dist: isort (>=5.11.5,<6.0.0) ; extra == "compiler"
Requires-Dist: jinja2 (>=3.0.3) ; extra == "compiler"
Requires-Dist: python-dateutil (>=2.8,<3.0)
Requires-Dist: typing-extensions (>=4.7.1,<5.0.0)
Project-URL: Repository, https://github.com/beam-cloud/python-betterproto
